branch_detective/__init__.py
branch_detective/__main__.py
branch_detective/commits.py
branch_detective/compare.py
branch_detective/description.py
branch_detective/repository.py
branch_detective-1.1.0.dist-info/LICENSE
branch_detective-1.1.0.dist-info/METADATA
branch_detective-1.1.0.dist-info/WHEEL
branch_detective-1.1.0.dist-info/entry_points.txt
branch_detective-1.1.0.dist-info/top_level.txt
branch_detective-1.1.0.dist-info/RECORD
