Metadata-Version: 2.1
Name: branch-detective
Version: 1.1.0
Summary: Detect which commits are absent between branches.
Home-page: https://github.com/codemouse92/branch-detective
Author: Jason C. McDonald
Author-email: codemouse92@outlook.com
Project-URL: Bug Reports, https://github.com/codemouse92/branch-detective/issues
Project-URL: Source, https://github.com/codemouse92/branch-detective
Keywords: utility git tool development
License-File: LICENSE
Requires-Dist: click
Requires-Dist: GitPython
Provides-Extra: test
Requires-Dist: pytest ; extra == 'test'
Requires-Dist: coverage ; extra == 'test'
Requires-Dist: tox ; extra == 'test'
